{
    "【一审法院查明】一审法院认定事实：卢学其作为投资人，思皇公司作为被投资人，银昶公司作为投资管理人于2016年8月5日签订《项目投资管理合同》（编号为银管字第6085184357号）；": 0,
    "合同约定：卢学其投资金额五万元，投资期限自2016年8月5日至2017年8月4日，投资收益率为1.5%/月，于每月20日前支付给卢学其；": 0,
    "思皇公司在投资到期后一次性归还卢学其投资款；": 0,
    "同时约定银昶公司对投资及投资回报承担连带返还责任；": 0,
    "三方约定因本合同产生的纠纷由顺义法院诉讼解决；": 0,
    "2016年8月5日，银昶公司向卢学其出具保证函，保证函约定：思皇公司若到期不能返还投资，银昶公司保证到期三日内无条件代为返还卢学其的投资和收益；": 0,
    "卢学其于合同签订当日向银昶公司支付五万元，四万元为现金，一万元为转账；": 1,
    "卢学其一审当庭陈述称，其并未参与过思皇公司的经营，三方签订的合同也没有约定任何风险，银昶公司自2016年8月5日至2017年4月20日均能按照合同约定支付利息，2017年4月21日之后的利息及本金银昶公司、思皇公司均未返还；": 1,
    "【本院查明】二审中，双方当事人没有提交新的证据；": 0,
    "本院对一审法院查明的事实予以确认；": 0
}